[
  {
    "descendant_group_id": "101200001",
    "descendant_group_name": "継承者グループ：レピック"
  },
  {
    "descendant_group_id": "101200002",
    "descendant_group_name": "継承者グループ：エイジャックス"
  },
  {
    "descendant_group_id": "101200003",
    "descendant_group_name": "継承者グループ：ビエッサー"
  },
  {
    "descendant_group_id": "101200005",
    "descendant_group_name": "継承者グループ：ジェイバー"
  },
  {
    "descendant_group_id": "101200006",
    "descendant_group_name": "継承者グループ：バニー"
  },
  {
    "descendant_group_id": "101200008",
    "descendant_group_name": "継承者グループ：フレイナ"
  },
  {
    "descendant_group_id": "101200009",
    "descendant_group_name": "継承者グループ：グライ"
  },
  {
    "descendant_group_id": "101200011",
    "descendant_group_name": "継承者グループ：シャレン"
  },
  {
    "descendant_group_id": "101200012",
    "descendant_group_name": "継承者グループ：ブレア"
  },
  {
    "descendant_group_id": "101200013",
    "descendant_group_name": "継承者グループ：バルビー"
  },
  {
    "descendant_group_id": "101200014",
    "descendant_group_name": "継承者グループ：カイル"
  },
  {
    "descendant_group_id": "101200015",
    "descendant_group_name": "継承者グループ：エシモ"
  },
  {
    "descendant_group_id": "101200016",
    "descendant_group_name": "継承者グループ：エンゾ"
  },
  {
    "descendant_group_id": "101200017",
    "descendant_group_name": "継承者グループ：ユジン"
  },
  {
    "descendant_group_id": "101200018",
    "descendant_group_name": "継承者グループ：ルーナ"
  },
  {
    "descendant_group_id": "101200021",
    "descendant_group_name": "継承者グループ：ヘイリー"
  },
  {
    "descendant_group_id": "101200024",
    "descendant_group_name": "継承者グループ：キーラン"
  },
  {
    "descendant_group_id": "101200026",
    "descendant_group_name": "継承者グループ：イネス"
  },
  {
    "descendant_group_id": "101200027",
    "descendant_group_name": "継承者グループ：セレナ"
  },
  {
    "descendant_group_id": "101200029",
    "descendant_group_name": "継承者グループ：ネール"
  },
  {
    "descendant_group_id": "101200031",
    "descendant_group_name": "継承者グループ：ハリス"
  },
  {
    "descendant_group_id": "101200032",
    "descendant_group_name": "継承者グループ：ダイア"
  }
]
