[
  {
    "descendant_group_id": "101200001",
    "descendant_group_name": "Gruppo Discendenti: Lepic"
  },
  {
    "descendant_group_id": "101200002",
    "descendant_group_name": "Gruppo Discendenti: Ajax"
  },
  {
    "descendant_group_id": "101200003",
    "descendant_group_name": "Gruppo Discendenti: Viessa"
  },
  {
    "descendant_group_id": "101200005",
    "descendant_group_name": "Gruppo Discendenti: Jayber"
  },
  {
    "descendant_group_id": "101200006",
    "descendant_group_name": "Gruppo Discendenti: Bunny"
  },
  {
    "descendant_group_id": "101200008",
    "descendant_group_name": "Gruppo Discendenti: Freyna"
  },
  {
    "descendant_group_id": "101200009",
    "descendant_group_name": "Gruppo Discendenti: Gley"
  },
  {
    "descendant_group_id": "101200011",
    "descendant_group_name": "Gruppo Discendenti: Sharen"
  },
  {
    "descendant_group_id": "101200012",
    "descendant_group_name": "Gruppo Discendenti: Blair"
  },
  {
    "descendant_group_id": "101200013",
    "descendant_group_name": "Gruppo Discendenti: Valby"
  },
  {
    "descendant_group_id": "101200014",
    "descendant_group_name": "Gruppo Discendenti: Kyle"
  },
  {
    "descendant_group_id": "101200015",
    "descendant_group_name": "Gruppo Discendenti: Esiemo"
  },
  {
    "descendant_group_id": "101200016",
    "descendant_group_name": "Gruppo Discendenti: Enzo"
  },
  {
    "descendant_group_id": "101200017",
    "descendant_group_name": "Gruppo Discendenti: Yujin"
  },
  {
    "descendant_group_id": "101200018",
    "descendant_group_name": "Gruppo Discendenti: Luna"
  },
  {
    "descendant_group_id": "101200021",
    "descendant_group_name": "Gruppo Discendenti: Hailey"
  },
  {
    "descendant_group_id": "101200024",
    "descendant_group_name": "Gruppo Discendenti: Keelan"
  },
  {
    "descendant_group_id": "101200026",
    "descendant_group_name": "Gruppo Discendenti: Ines"
  },
  {
    "descendant_group_id": "101200027",
    "descendant_group_name": "Gruppo Discendenti: Serena"
  },
  {
    "descendant_group_id": "101200029",
    "descendant_group_name": "Gruppo Discendenti: Nell"
  },
  {
    "descendant_group_id": "101200031",
    "descendant_group_name": "Gruppo Discendenti: Harris"
  },
  {
    "descendant_group_id": "101200032",
    "descendant_group_name": "Gruppo Discendenti: Dia"
  }
]
